<?xml version="1.0" encoding="UTF-8"?>

<!--suppress SpringBeanNameConventionInspection -->
<beans
    xmlns:xsi="http://www.w3.org/2001/XMLSchema-instance"
    xmlns="http://www.springframework.org/schema/beans"
    xmlns:util="http://www.springframework.org/schema/util"
    xmlns:property="http://www.springframework.org/schema/p"
    xmlns:context="http://www.springframework.org/schema/context"

    xsi:schemaLocation="
        http://www.springframework.org/schema/beans
		http://www.springframework.org/schema/beans/spring-beans-3.0.xsd
		http://www.springframework.org/schema/util
		http://www.springframework.org/schema/util/spring-util.xsd
		http://www.springframework.org/schema/context
		http://www.springframework.org/schema/context/spring-context-3.0.xsd">

    <description>This file is for deploying ikube into a cluster using ssh and scp.</description>

    <context:property-placeholder
        location="
            classpath*:spring.properties,
            classpath*:deploy/spring.properties,
            classpath*:spring-local.properties,
            classpath*:**/spring-local.properties,
            classpath*:**/**/spring-local.properties,
            */**/spring-local.properties"
        properties-ref="ikube.toolkit.PropertyConfigurer"/>

    <bean
        id="ikube.toolkit.Logging"
        class="org.springframework.beans.factory.config.MethodInvokingFactoryBean"
        property:staticMethod="ikube.toolkit.LOGGING.configure"/>

    <!-- This bean will look through the classpath and load every Spring properties file it finds. -->
    <bean
        id="ikube.toolkit.PropertyConfigurer"
        class="ikube.toolkit.PropertyConfigurer"
        property:fileNamePattern="spring.properties"
        lazy-init="false"
        init-method="initialize"/>

    <!-- Turn on AspectJ @Configurable support -->
    <context:spring-configured/>
    <context:component-scan base-package="ikube.deploy"/>

    <bean
        class="ikube.deploy.Deployer"
        property:parallel="${in-parallel}"
        property:maxWaitTime="60"/>

    <!-- Cluster servers one, two and three on the 32 core machine -->

    <!-- One -->
    <bean
        id="server-one"
        name="server-one"
        class="ikube.deploy.model.Server"
	    property:name="server-one"
        property:ip="${server-system-ip}"
        property:username="${username}"
        property:password="${password}"
        property:actions-ref="actions-one"/>
    <util:list id="actions-one">
        <ref local="stop-action-one"/>
        <ref local="clean-action-one"/>
        <ref local="copy-action-one"/>
        <ref local="start-action-one"/>
    </util:list>
    <bean
        id="stop-action-one"
        name="stop-action-one"
        class="ikube.deploy.action.CmdAction"
        property:sleep="${sleep}"
        property:breakOnError="true"
        property:commands-ref="stop-commands-one"/>
    <util:list id="stop-commands-one">
        <value>${tomcat-one-shutdown};</value>
        <value>${tomcat-one-kill};</value>
    </util:list>
    <bean
        id="clean-action-one"
        name="clean-action-one"
        class="ikube.deploy.action.CmdAction"
        property:sleep="${sleep}"
        property:breakOnError="true"
        property:commands-ref="clean-commands-one"/>
    <util:list id="clean-commands-one">
        <value>chmod 777 -R ${tomcat-one};</value>
        <value>rm -rf ${tomcat-one-bin}/ikube/*;</value>
        <value>rm -rf ${tomcat-one-webapps}/ikube*;</value>
        <value>rm -rf ${tomcat-one}/logs/*;</value>
        <value>rm -rf ${tomcat-one}/temp/*;</value>
        <value>rm -rf ${tomcat-one}/work/*;</value>
    </util:list>
    <bean
        id="copy-action-one"
        name="copy-action-one"
        class="ikube.deploy.action.CopyAction"
        property:sleep="${sleep}"
        property:breakOnError="true"
        property:files-ref="files-one"
        property:directories-ref="directories-one"/>
    <util:map id="files-one">
        <entry key="${tail-script}" value="${tomcat-one-bin}"/>
        <entry key="${target-directory}/${ikube-war}" value="${tomcat-one-webapps}"/>
        <!-- This over writes the properties specific for the target environment -->
        <entry key="${resources-directory}/environments/sys/spring.properties" value="${tomcat-one-bin}/ikube/common"/>
    </util:map>
    <util:map id="directories-one">
        <entry key="${resources-directory}/ikube" value="${tomcat-one-bin}"/>
        <entry key="${resources-directory}/analytics" value="${tomcat-one-bin}/ikube"/>
        <entry key="${resources-directory}/indexes/integration" value="${tomcat-one-bin}/ikube"/>
        <entry key="${resources-directory}/indexes/production" value="${tomcat-one-bin}/ikube"/>
        <entry key="${resources-directory}/indexes/twitter" value="${tomcat-one-bin}/ikube"/>
        <entry key="${resources-directory}/indexes/bosal" value="${tomcat-one-bin}/ikube"/>
    </util:map>
    <bean
        id="start-action-one"
        name="start-action-one"
        class="ikube.deploy.action.CmdAction"
        property:sleep="${sleep}"
        property:breakOnError="true"
        property:commands-ref="start-commands-one"/>
    <util:list id="start-commands-one">
        <value>${tomcat-one-chmod}</value>
        <value>cp /home/mineco-regression.arff ./ikube/analytics</value>
        <value>${tomcat-one-startup}</value>
    </util:list>
    <!-- End one -->

    <!-- Two -->
    <bean
        id="server-two"
        name="server-two"
        class="ikube.deploy.model.Server"
    	property:name="server-two"
        property:ip="${server-system-ip}"
        property:username="${username}"
        property:password="${password}"
        property:actions-ref="actions-two"/>
    <util:list id="actions-two">
        <ref local="stop-action-two"/>
        <ref local="clean-action-two"/>
        <ref local="copy-action-two"/>
        <ref local="start-action-two"/>
    </util:list>
    <bean
        id="stop-action-two"
        name="stop-action-two"
        class="ikube.deploy.action.CmdAction"
        property:sleep="${sleep}"
        property:breakOnError="true"
        property:commands-ref="stop-commands-two"/>
    <util:list id="stop-commands-two">
        <value>${tomcat-two-shutdown};</value>
        <value>${tomcat-two-kill};</value>
    </util:list>
    <bean
        id="clean-action-two"
        name="clean-action-two"
        class="ikube.deploy.action.CmdAction"
        property:sleep="${sleep}"
        property:breakOnError="true"
        property:commands-ref="clean-commands-two"/>
    <util:list id="clean-commands-two">
        <value>chmod 777 -R ${tomcat-two};</value>
        <value>rm -rf ${tomcat-two-bin}/ikube/*;</value>
        <value>rm -rf ${tomcat-two-webapps}/ikube*;</value>
        <value>rm -rf ${tomcat-two}/logs/*;</value>
        <value>rm -rf ${tomcat-two}/temp/*;</value>
        <value>rm -rf ${tomcat-two}/work/*;</value>
    </util:list>
    <bean
        id="copy-action-two"
        name="copy-action-two"
        class="ikube.deploy.action.CopyAction"
        property:sleep="${sleep}"
        property:breakOnError="true"
        property:files-ref="files-two"
        property:directories-ref="directories-two"/>
    <util:map id="files-two">
        <entry key="${tail-script}" value="${tomcat-two-bin}"/>
        <entry key="${target-directory}/${ikube-war}" value="${tomcat-two-webapps}"/>
        <!-- This over writes the properties specific for the target environment -->
        <entry key="${resources-directory}/environments/sys/spring.properties" value="${tomcat-two-bin}/ikube/common"/>
    </util:map>
    <util:map id="directories-two">
        <entry key="${resources-directory}/ikube" value="${tomcat-two-bin}"/>
        <entry key="${resources-directory}/analytics" value="${tomcat-two-bin}/ikube"/>
        <entry key="${resources-directory}/indexes/integration" value="${tomcat-two-bin}/ikube"/>
        <entry key="${resources-directory}/indexes/production" value="${tomcat-two-bin}/ikube"/>
        <entry key="${resources-directory}/indexes/twitter" value="${tomcat-two-bin}/ikube"/>
        <entry key="${resources-directory}/indexes/bosal" value="${tomcat-two-bin}/ikube"/>
    </util:map>
    <bean
        id="start-action-two"
        name="start-action-two"
        class="ikube.deploy.action.CmdAction"
        property:sleep="600000"
        property:breakOnError="true"
        property:commands-ref="start-commands-two"/>
    <util:list id="start-commands-two">
        <value>${tomcat-two-chmod}</value>
        <value>cp /home/mineco-regression.arff ./ikube/analytics</value>
        <value>${tomcat-two-startup}</value>
    </util:list>
    <!-- End two -->

    <!-- Three -->
    <bean
        id="server-three"
        name="server-three"
        class="ikube.deploy.model.Server"
    	property:name="server-three"
        property:ip="${server-system-ip}"
        property:username="${username}"
        property:password="${password}"
        property:actions-ref="actions-three"/>
    <util:list id="actions-three">
        <ref local="stop-action-three"/>
        <ref local="clean-action-three"/>
        <ref local="copy-action-three"/>
        <ref local="start-action-three"/>
    </util:list>
    <bean
        id="stop-action-three"
        name="stop-action-three"
        class="ikube.deploy.action.CmdAction"
        property:sleep="${sleep}"
        property:breakOnError="true"
        property:commands-ref="stop-commands-three"/>
    <util:list id="stop-commands-three">
        <value>${tomcat-three-shutdown};</value>
        <value>${tomcat-three-kill};</value>
    </util:list>
    <bean
        id="clean-action-three"
        name="clean-action-three"
        class="ikube.deploy.action.CmdAction"
        property:sleep="${sleep}"
        property:breakOnError="true"
        property:commands-ref="clean-commands-three"/>
    <util:list id="clean-commands-three">
        <value>chmod 777 -R ${tomcat-three};</value>
        <value>rm -rf ${tomcat-three-bin}/ikube/*;</value>
        <value>rm -rf ${tomcat-three-webapps}/ikube*;</value>
        <value>rm -rf ${tomcat-three}/logs/*;</value>
        <value>rm -rf ${tomcat-three}/temp/*;</value>
        <value>rm -rf ${tomcat-three}/work/*;</value>
    </util:list>
    <bean
        id="copy-action-three"
        name="copy-action-three"
        class="ikube.deploy.action.CopyAction"
        property:sleep="${sleep}"
        property:breakOnError="true"
        property:files-ref="files-three"
        property:directories-ref="directories-three"/>
    <util:map id="files-three">
        <entry key="${tail-script}" value="${tomcat-three-bin}"/>
        <entry key="${target-directory}/${ikube-war}" value="${tomcat-three-webapps}"/>
        <!-- This over writes the properties specific for the target environment -->
        <entry key="${resources-directory}/environments/sys/spring.properties"
               value="${tomcat-three-bin}/ikube/common"/>
    </util:map>
    <util:map id="directories-three">
        <entry key="${resources-directory}/ikube" value="${tomcat-three-bin}"/>
        <entry key="${resources-directory}/analytics" value="${tomcat-three-bin}/ikube"/>
        <entry key="${resources-directory}/indexes/integration" value="${tomcat-three-bin}/ikube"/>
        <entry key="${resources-directory}/indexes/production" value="${tomcat-three-bin}/ikube"/>
        <entry key="${resources-directory}/indexes/twitter" value="${tomcat-three-bin}/ikube"/>
        <entry key="${resources-directory}/indexes/bosal" value="${tomcat-three-bin}/ikube"/>
    </util:map>
    <bean
        id="start-action-three"
        name="start-action-three"
        class="ikube.deploy.action.CmdAction"
        property:sleep="120000"
        property:breakOnError="true"
        property:commands-ref="start-commands-three"/>
    <util:list id="start-commands-three">
        <value>${tomcat-three-chmod}</value>
        <value>cp /home/mineco-regression.arff ./ikube/analytics</value>
        <value>${tomcat-three-startup}</value>
    </util:list>
    <!-- End three -->

    <!-- Production -->
    <bean
        id="server-production"
        name="server-production"
        class="ikube.deploy.model.Server"
	    property:name="server-production"
        property:ip="${server-production-ip}"
        property:username="${username}"
        property:password="${password}"
        property:actions-ref="actions-production"/>
    <util:list id="actions-production">
        <ref local="stop-action-production"/>
        <ref local="clean-action-production"/>
        <ref local="copy-action-production"/>
        <ref local="start-action-production"/>
    </util:list>
    <bean
        id="stop-action-production"
        name="stop-action-production"
        class="ikube.deploy.action.CmdAction"
        property:sleep="${sleep}"
        property:breakOnError="false"
        property:commands-ref="stop-commands-production"/>
    <util:list id="stop-commands-production">
        <value>${tomcat-production-shutdown};</value>
        <value>${tomcat-production-kill};</value>
    </util:list>
    <bean
        id="clean-action-production"
        name="clean-action-production"
        class="ikube.deploy.action.CmdAction"
        property:sleep="${sleep}"
        property:breakOnError="false"
        property:commands-ref="clean-commands-production"/>
    <util:list id="clean-commands-production">
        <value>chmod 777 -R ${tomcat-production};</value>
        <value>rm -rf ${tomcat-production-bin}/ikube/*;</value>
        <value>rm -rf ${tomcat-production-webapps}/ikube*;</value>
        <value>rm -rf ${tomcat-production}/logs/*;</value>
        <value>rm -rf ${tomcat-production}/temp/*;</value>
        <value>rm -rf ${tomcat-production}/work/*;</value>
    </util:list>
    <bean
        id="copy-action-production"
        name="copy-action-production"
        class="ikube.deploy.action.CopyAction"
        property:sleep="${sleep}"
        property:breakOnError="false"
        property:files-ref="files-production"
        property:directories-ref="directories-production"/>
    <util:map id="files-production">
        <entry key="${tail-script}" value="${tomcat-production-bin}"/>
        <entry key="${target-directory}/${ikube-war}" value="${tomcat-production-webapps}"/>
        <!-- This over writes the properties specific for the target environment -->
        <entry key="${resources-directory}/environments/prd/spring.properties" value="${tomcat-production-bin}/ikube/common"/>
    </util:map>
    <util:map id="directories-production">
        <entry key="${resources-directory}/ikube" value="${tomcat-production-bin}"/>
        <entry key="${resources-directory}/analytics" value="${tomcat-production-bin}/ikube"/>
        <entry key="${resources-directory}/indexes/production" value="${tomcat-production-bin}/ikube"/>
        <entry key="${resources-directory}/indexes/mineco" value="${tomcat-production-bin}/ikube"/>
        <!--<entry key="${resources-directory}/indexes/twitter" value="${tomcat-production-bin}/ikube"/>-->
    </util:map>
    <bean
        id="start-action-production"
        name="start-action-production"
        class="ikube.deploy.action.CmdAction"
        property:sleep="${sleep}"
        property:breakOnError="false"
        property:commands-ref="start-commands-production"/>
    <util:list id="start-commands-production">
        <value>${tomcat-production-chmod}</value>
        <value>cp /home/data/mineco-regression.arff ${tomcat-production-bin}/ikube/analytics</value>
        <value>${tomcat-production-startup}</value>
    </util:list>
    <!-- End production -->

    <!-- Site -->
    <bean
        id="server-site"
        name="server-site"
        class="ikube.deploy.model.Server"
        property:name="server-site"
        property:ip="${server-site-ip}"
        property:username="${username}"
        property:password="${password}"
        property:actions-ref="actions-site"/>
    <util:list id="actions-site">
        <!-- ref local="stop-action-site"/ -->
        <ref local="clean-action-site"/>
        <ref local="copy-action-site"/>
        <!-- ref local="start-action-site"/ -->
    </util:list>
    <bean
        id="stop-action-site"
        name="stop-action-site"
        class="ikube.deploy.action.CmdAction"
        property:sleep="${sleep}"
        property:breakOnError="false"
        property:commands-ref="stop-commands-site"/>
    <util:list id="stop-commands-site">
        <value>${tomcat-site-shutdown};</value>
        <value>${tomcat-site-kill};</value>
    </util:list>
    <bean
        id="clean-action-site"
        name="clean-action-site"
        class="ikube.deploy.action.CmdAction"
        property:sleep="${sleep}"
        property:breakOnError="false"
        property:commands-ref="clean-commands-site"/>
    <util:list id="clean-commands-site">
        <value>chmod 777 -R ${tomcat-site};</value>
        <value>rm -rf ${tomcat-site-webapps}/site*;</value>
    </util:list>
    <bean
        id="copy-action-site"
        name="copy-action-site"
        class="ikube.deploy.action.CopyAction"
        property:sleep="${sleep}"
        property:breakOnError="false"
        property:files-ref="files-site"/>
    <util:map id="files-site">
        <entry key="${target-directory-site}/${site-war}" value="${tomcat-site-webapps}"/>
    </util:map>
    <bean
        id="start-action-site"
        name="start-action-site"
        class="ikube.deploy.action.CmdAction"
        property:sleep="${sleep}"
        property:breakOnError="false"
        property:commands-ref="start-commands-site"/>
    <util:list id="start-commands-site">
        <value>${tomcat-site-chmod}</value>
        <value>${tomcat-site-startup}</value>
    </util:list>
    <!-- End site -->

    <!-- FIS -->
    <bean
        id="server-fis"
        name="server-fis"
        class="ikube.deploy.model.Server"
        property:name="server-fis"
        property:ip="${server-fis-ip}"
        property:username="${username}"
        property:password="${password}"
        property:actions-ref="actions-fis"/>
    <util:list id="actions-fis">
        <ref local="stop-action-fis"/>
        <ref local="clean-action-fis"/>
        <ref local="copy-action-fis"/>
        <ref local="start-action-fis"/>
    </util:list>
    <bean
        id="stop-action-fis"
        name="stop-action-fis"
        class="ikube.deploy.action.CmdAction"
        property:sleep="${sleep}"
        property:breakOnError="false"
        property:commands-ref="stop-commands-fis"/>
    <util:list id="stop-commands-fis">
        <value>${tomcat-fis-shutdown};</value>
        <value>${tomcat-fis-kill};</value>
    </util:list>
    <bean
        id="clean-action-fis"
        name="clean-action-fis"
        class="ikube.deploy.action.CmdAction"
        property:sleep="${sleep}"
        property:breakOnError="false"
        property:commands-ref="clean-commands-fis"/>
    <util:list id="clean-commands-fis">
        <value>chmod 777 -R ${tomcat-fis};</value>
        <value>rm -rf ${tomcat-fis-bin}/ikube/*;</value>
        <value>rm -rf ${tomcat-fis-webapps}/ikube*;</value>
        <value>rm -rf ${tomcat-fis}/logs/*;</value>
        <value>rm -rf ${tomcat-fis}/temp/*;</value>
        <value>rm -rf ${tomcat-fis}/work/*;</value>
    </util:list>
    <bean
        id="copy-action-fis"
        name="copy-action-fis"
        class="ikube.deploy.action.CopyAction"
        property:sleep="${sleep}"
        property:breakOnError="false"
        property:files-ref="files-fis"
        property:directories-ref="directories-fis"/>
    <util:map id="files-fis">
        <entry key="${tail-script}" value="${tomcat-fis-bin}"/>
        <entry key="${target-directory}/${ikube-war}" value="${tomcat-fis-webapps}"/>
        <!-- This over writes the properties specific for the target environment -->
        <entry key="${resources-directory}/environments/prd/spring.properties" value="${tomcat-fis-bin}/ikube/common"/>
        <entry key="${resources-directory}/indexes/production/spring.properties" value="${tomcat-fis-bin}/ikube/production"/>
        <entry key="${resources-directory}/indexes/production/spring-auto.xml" value="${tomcat-fis-bin}/ikube/production"/>
    </util:map>
    <util:map id="directories-fis">
        <entry key="${resources-directory}/ikube" value="${tomcat-fis-bin}"/>
        <entry key="${resources-directory}/analytics" value="${tomcat-fis-bin}/ikube"/>
        <entry key="${resources-directory}/indexes/fis" value="${tomcat-fis-bin}/ikube"/>
    </util:map>
    <bean
        id="start-action-fis"
        name="start-action-fis"
        class="ikube.deploy.action.CmdAction"
        property:sleep="${sleep}"
        property:breakOnError="false"
        property:commands-ref="start-commands-fis"/>
    <util:list id="start-commands-fis">
        <value>${tomcat-fis-chmod}</value>
        <value>${tomcat-fis-startup}</value>
    </util:list>
    <!-- End FIS -->

</beans>